InfixParser.cpython-39-x86_64-linux-gnu.so
InfixParser-3.1.4.dist-info/LICENSE
InfixParser-3.1.4.dist-info/METADATA
InfixParser-3.1.4.dist-info/top_level.txt
InfixParser-3.1.4.dist-info/RECORD
InfixParser-3.1.4.dist-info/WHEEL
