Metadata-Version: 2.1
Name: InfixParser
Version: 3.1.4
Summary: Evaluate infix math expresion in python with ease.
Home-page: https://github.com/KJ002/Py-MathParser
Author: James Butcher
Author-email: jamesbutcher167@gmail.com
License: MIT
Platform: UNKNOWN
Classifier: Programming Language :: Python :: 3
Classifier: Intended Audience :: Developers
License-File: LICENSE
